sgpt/__init__.py
sgpt/__main__.py
sgpt/__version__.py
sgpt/app.py
sgpt/cache.py
sgpt/config.py
sgpt/cost_estimator.py
sgpt/function.py
sgpt/integration.py
sgpt/plan.py
sgpt/plan_parser.py
sgpt/plan_ui.py
sgpt/printer.py
sgpt/role.py
sgpt/utils.py
sgpt/handlers/__init__.py
sgpt/handlers/chat_handler.py
sgpt/handlers/default_handler.py
sgpt/handlers/handler.py
sgpt/handlers/plan_execute_handler.py
sgpt/handlers/repl_handler.py
sgpt/llm_functions/__init__.py
sgpt/llm_functions/init_functions.py
sgpt/llm_functions/common/execute_shell.py
sgpt/llm_functions/mac/apple_script.py
shell_gpt_deluxe-0.1.1.dist-info/METADATA
shell_gpt_deluxe-0.1.1.dist-info/WHEEL
shell_gpt_deluxe-0.1.1.dist-info/entry_points.txt
shell_gpt_deluxe-0.1.1.dist-info/licenses/LICENSE
shell_gpt_deluxe-0.1.1.dist-info/RECORD
