Metadata-Version: 2.4
Name: shell-gpt-deluxe
Version: 0.1.1
Summary: A command-line productivity tool powered by large language models with autonomous multi-step plan-execute mode. Fork of shell-gpt with plan-execute extension.
Project-URL: homepage, https://github.com/Key-J/shell_gpt_deluxe
Project-URL: repository, https://github.com/Key-J/shell_gpt_deluxe
Project-URL: documentation, https://github.com/Key-J/shell_gpt_deluxe/blob/main/README.md
Project-URL: original, https://github.com/TheR1D/shell_gpt
Author-email: Farkhod Sadykov <farkhod@sadykov.dev>
License-Expression: MIT
License-File: LICENSE
Keywords: agent,autonomous,cheet-sheet,cli,gpt,ollama,openai,planning,productivity,shell
Classifier: Intended Audience :: Developers
Classifier: Intended Audience :: Information Technology
Classifier: Intended Audience :: System Administrators
Classifier: License :: OSI Approved :: MIT License
Classifier: Operating System :: OS Independent
Classifier: Programming Language :: Python :: 3.10
Classifier: Programming Language :: Python :: 3.11
Classifier: Programming Language :: Python :: 3.12
Classifier: Programming Language :: Python :: 3.13
Classifier: Topic :: Software Development
Requires-Python: >=3.10
Requires-Dist: click<9.0.0,>=7.1.1
Requires-Dist: distro<2.0.0,>=1.8.0
Requires-Dist: instructor<2.0.0,>=1.0.0
Requires-Dist: openai<2.0.0,>=1.34.0
Requires-Dist: prompt-toolkit>=3.0.51
Requires-Dist: pyreadline3<4.0.0,>=3.4.1; sys_platform == 'win32'
Requires-Dist: rich<14.0.0,>=13.1.0
Requires-Dist: typer<1.0.0,>=0.7.0
Provides-Extra: dev
Requires-Dist: pre-commit<4.0.0,>=3.1.1; extra == 'dev'
Requires-Dist: ruff==0.0.256; extra == 'dev'
Provides-Extra: litellm
Requires-Dist: litellm==1.42.5; extra == 'litellm'
Provides-Extra: test
Requires-Dist: black==23.1.0; extra == 'test'
Requires-Dist: codespell<3.0.0,>=2.2.5; extra == 'test'
Requires-Dist: isort<6.0.0,>=5.12.0; extra == 'test'
Requires-Dist: mypy==1.1.1; extra == 'test'
Requires-Dist: pytest<8.0.0,>=7.2.2; extra == 'test'
Requires-Dist: requests-mock[fixture]<2.0.0,>=1.10.0; extra == 'test'
Requires-Dist: types-requests==2.28.11.17; extra == 'test'
